tests/__init__.py
tests/conftest.py
tests/test_embedding.py
tests/test_embeddingset.py
tests/test_helpers.py
tests/test_import_error.py
tests/test_transformers.py
tests/test_documentation/__init__.py
tests/test_documentation/test_apidoc.py
tests/test_documentation/test_docs.py
tests/test_lang/__init__.py
tests/test_lang/test_countvector_lang.py
tests/test_lang/test_fasttext_lang.py
tests/test_lang/test_gensim.py
tests/test_lang/test_hftransformers_lang.py
tests/test_lang/test_pblang.py
tests/test_lang/test_sent_tfm.py
tests/test_lang/test_spacy_language.py
tests/test_lang/test_tfhub_lang.py
tests/test_lang/test_tfidflang.py
tests/test_lang/test_universal_sentence_encoder.py
tests/test_plotting/__init__.py
tests/test_plotting/test_dist_sim_plots.py
tests/test_plotting/test_altair/__init__.py
tests/test_plotting/test_altair/common.py
tests/test_plotting/test_altair/test_embeddingset_plot_interactive.py
tests/test_plotting/test_altair/test_embeddingset_plot_interactive_matrix.py
tests/test_plotting/test_matplotlib/__init__.py
tests/test_plotting/test_matplotlib/common.py
tests/test_plotting/test_matplotlib/test_embedding_plot.py
tests/test_plotting/test_matplotlib/test_embeddingset_plot.py
tests/test_plotting/test_matplotlib/test_plot_3d.py
tests/test_sklearn/__init__.py
tests/test_sklearn/test_fasttext_sklearn.py
tests/test_sklearn/test_simple_pipeline.py
whatlies/__init__.py
whatlies/common.py
whatlies/embedding.py
whatlies/embeddingset.py
whatlies/error.py
whatlies/helpers.py
whatlies/plotting.py
whatlies/language/__init__.py
whatlies/language/_bpemblang.py
whatlies/language/_common.py
whatlies/language/_convert_lang.py
whatlies/language/_countvector_lang.py
whatlies/language/_diet_lang.py
whatlies/language/_fasttext_lang.py
whatlies/language/_floret_lang.py
whatlies/language/_gensim_lang.py
whatlies/language/_hftransformers_lang.py
whatlies/language/_sense2vec_lang.py
whatlies/language/_sentence_encode_lang.py
whatlies/language/_sentencetfm_lang.py
whatlies-0.7.0.dist-info/LICENSE
whatlies-0.7.0.dist-info/METADATA
whatlies-0.7.0.dist-info/WHEEL
whatlies-0.7.0.dist-info/top_level.txt
whatlies-0.7.0.dist-info/RECORD
