Metadata-Version: 2.1
Name: whatlies
Version: 0.7.0
Summary: Tools to help uncover `whatlies` in word embeddings.
Home-page: https://koaning.github.io/whatlies/
Author: Vincent D. Warmerdam
License: UNKNOWN
Project-URL: Documentation, https://koaning.github.io/whatlies/
Project-URL: Source Code, https://github.com/koaning/whatlies/
Project-URL: Issue Tracker, https://github.com/koaning/whatlies/issues
Platform: UNKNOWN
Classifier: Intended Audience :: Science/Research
Classifier: Programming Language :: Python :: 3
Classifier: Programming Language :: Python :: 3.7
Classifier: Programming Language :: Python :: 3.8
Classifier: Programming Language :: Python :: 3.9
Classifier: License :: OSI Approved :: MIT License
Classifier: Topic :: Scientific/Engineering
Classifier: Topic :: Scientific/Engineering :: Artificial Intelligence
License-File: LICENSE
Requires-Dist: scikit-learn (>=1.0.0)
Requires-Dist: altair (>=4.2.0)
Requires-Dist: matplotlib (>=3.5.0)
Requires-Dist: bpemb (>=0.3.0)
Requires-Dist: gensim (~=3.8.3)
Provides-Extra: all
Requires-Dist: tensorflow (<2.10,>=2.9.0) ; extra == 'all'
Requires-Dist: tensorflow-text (<2.10,>=2.9.0) ; extra == 'all'
Requires-Dist: tensorflow-hub (<1.0,>=0.12.0) ; extra == 'all'
Requires-Dist: transformers (>=4.19.0) ; extra == 'all'
Requires-Dist: sense2vec (>=2.0.0) ; extra == 'all'
Requires-Dist: spacy (>=3.3.0) ; extra == 'all'
Requires-Dist: spacy-lookups-data (>=0.3.2) ; extra == 'all'
Requires-Dist: sentence-transformers (>=2.2.0) ; extra == 'all'
Requires-Dist: fasttext (~=0.9.1) ; extra == 'all'
Requires-Dist: umap-learn (>=0.5.0) ; extra == 'all'
Requires-Dist: floret (>=0.10.1) ; extra == 'all'
Provides-Extra: base
Requires-Dist: scikit-learn (>=1.0.0) ; extra == 'base'
Requires-Dist: altair (>=4.2.0) ; extra == 'base'
Requires-Dist: matplotlib (>=3.5.0) ; extra == 'base'
Requires-Dist: bpemb (>=0.3.0) ; extra == 'base'
Requires-Dist: gensim (~=3.8.3) ; extra == 'base'
Provides-Extra: dev
Requires-Dist: mkdocs (==1.1) ; extra == 'dev'
Requires-Dist: mkdocs-material (==4.6.3) ; extra == 'dev'
Requires-Dist: mkdocstrings (==0.8.0) ; extra == 'dev'
Requires-Dist: jupyterlab (>=0.35.4) ; extra == 'dev'
Requires-Dist: nbstripout (>=0.3.7) ; extra == 'dev'
Requires-Dist: nbval (>=0.9.5) ; extra == 'dev'
Requires-Dist: torch (>=1.11.0) ; extra == 'dev'
Requires-Dist: flake8 (>=3.6.0) ; extra == 'dev'
Requires-Dist: pytest (>=4.0.2) ; extra == 'dev'
Requires-Dist: black (>=19.3b0) ; extra == 'dev'
Requires-Dist: pytest-cov (>=2.6.1) ; extra == 'dev'
Requires-Dist: pre-commit (>=2.2.0) ; extra == 'dev'
Requires-Dist: tensorflow (<2.10,>=2.9.0) ; extra == 'dev'
Requires-Dist: tensorflow-text (<2.10,>=2.9.0) ; extra == 'dev'
Requires-Dist: tensorflow-hub (<1.0,>=0.12.0) ; extra == 'dev'
Requires-Dist: transformers (>=4.19.0) ; extra == 'dev'
Requires-Dist: sense2vec (>=2.0.0) ; extra == 'dev'
Requires-Dist: spacy (>=3.3.0) ; extra == 'dev'
Requires-Dist: spacy-lookups-data (>=0.3.2) ; extra == 'dev'
Requires-Dist: sentence-transformers (>=2.2.0) ; extra == 'dev'
Requires-Dist: fasttext (~=0.9.1) ; extra == 'dev'
Requires-Dist: umap-learn (>=0.5.0) ; extra == 'dev'
Requires-Dist: floret (>=0.10.1) ; extra == 'dev'
Provides-Extra: docs
Requires-Dist: mkdocs (==1.1) ; extra == 'docs'
Requires-Dist: mkdocs-material (==4.6.3) ; extra == 'docs'
Requires-Dist: mkdocstrings (==0.8.0) ; extra == 'docs'
Requires-Dist: jupyterlab (>=0.35.4) ; extra == 'docs'
Requires-Dist: nbstripout (>=0.3.7) ; extra == 'docs'
Requires-Dist: nbval (>=0.9.5) ; extra == 'docs'
Provides-Extra: floret
Requires-Dist: fasttext (~=0.9.1) ; extra == 'floret'
Requires-Dist: floret (>=0.10.1) ; extra == 'floret'
Provides-Extra: sense2vec
Requires-Dist: scikit-learn (>=1.0.0) ; extra == 'sense2vec'
Requires-Dist: altair (>=4.2.0) ; extra == 'sense2vec'
Requires-Dist: matplotlib (>=3.5.0) ; extra == 'sense2vec'
Requires-Dist: bpemb (>=0.3.0) ; extra == 'sense2vec'
Requires-Dist: gensim (~=3.8.3) ; extra == 'sense2vec'
Requires-Dist: sense2vec (>=2.0.0) ; extra == 'sense2vec'
Requires-Dist: spacy (>=3.3.0) ; extra == 'sense2vec'
Requires-Dist: spacy-lookups-data (>=0.3.2) ; extra == 'sense2vec'
Provides-Extra: sentence_tfm
Requires-Dist: scikit-learn (>=1.0.0) ; extra == 'sentence_tfm'
Requires-Dist: altair (>=4.2.0) ; extra == 'sentence_tfm'
Requires-Dist: matplotlib (>=3.5.0) ; extra == 'sentence_tfm'
Requires-Dist: bpemb (>=0.3.0) ; extra == 'sentence_tfm'
Requires-Dist: gensim (~=3.8.3) ; extra == 'sentence_tfm'
Requires-Dist: sentence-transformers (>=2.2.0) ; extra == 'sentence_tfm'
Provides-Extra: spacy
Requires-Dist: scikit-learn (>=1.0.0) ; extra == 'spacy'
Requires-Dist: altair (>=4.2.0) ; extra == 'spacy'
Requires-Dist: matplotlib (>=3.5.0) ; extra == 'spacy'
Requires-Dist: bpemb (>=0.3.0) ; extra == 'spacy'
Requires-Dist: gensim (~=3.8.3) ; extra == 'spacy'
Requires-Dist: spacy (>=3.3.0) ; extra == 'spacy'
Requires-Dist: spacy-lookups-data (>=0.3.2) ; extra == 'spacy'
Provides-Extra: test
Requires-Dist: torch (>=1.11.0) ; extra == 'test'
Requires-Dist: flake8 (>=3.6.0) ; extra == 'test'
Requires-Dist: pytest (>=4.0.2) ; extra == 'test'
Requires-Dist: black (>=19.3b0) ; extra == 'test'
Requires-Dist: pytest-cov (>=2.6.1) ; extra == 'test'
Requires-Dist: nbval (>=0.9.5) ; extra == 'test'
Requires-Dist: pre-commit (>=2.2.0) ; extra == 'test'
Provides-Extra: tfhub
Requires-Dist: scikit-learn (>=1.0.0) ; extra == 'tfhub'
Requires-Dist: altair (>=4.2.0) ; extra == 'tfhub'
Requires-Dist: matplotlib (>=3.5.0) ; extra == 'tfhub'
Requires-Dist: bpemb (>=0.3.0) ; extra == 'tfhub'
Requires-Dist: gensim (~=3.8.3) ; extra == 'tfhub'
Requires-Dist: tensorflow (<2.10,>=2.9.0) ; extra == 'tfhub'
Requires-Dist: tensorflow-text (<2.10,>=2.9.0) ; extra == 'tfhub'
Requires-Dist: tensorflow-hub (<1.0,>=0.12.0) ; extra == 'tfhub'
Provides-Extra: transformers
Requires-Dist: scikit-learn (>=1.0.0) ; extra == 'transformers'
Requires-Dist: altair (>=4.2.0) ; extra == 'transformers'
Requires-Dist: matplotlib (>=3.5.0) ; extra == 'transformers'
Requires-Dist: bpemb (>=0.3.0) ; extra == 'transformers'
Requires-Dist: gensim (~=3.8.3) ; extra == 'transformers'
Requires-Dist: transformers (>=4.19.0) ; extra == 'transformers'
Provides-Extra: umap
Requires-Dist: scikit-learn (>=1.0.0) ; extra == 'umap'
Requires-Dist: altair (>=4.2.0) ; extra == 'umap'
Requires-Dist: matplotlib (>=3.5.0) ; extra == 'umap'
Requires-Dist: bpemb (>=0.3.0) ; extra == 'umap'
Requires-Dist: gensim (~=3.8.3) ; extra == 'umap'
Requires-Dist: umap-learn (>=0.5.0) ; extra == 'umap'
